wd360/__init__.py
wd360/cli.py
wd360/config/__init__.py
wd360/config/models.py
wd360/modules/__init__.py
wd360/modules/azure_function_app_ai_host/__init__.py
wd360/modules/azure_function_app_ai_host/builder.py
wd360/modules/azure_function_app_ai_host/naming.py
wd360/modules/azure_vm_ai_host/__init__.py
wd360/modules/azure_vm_ai_host/builder.py
wd360/modules/azure_vm_ai_host/naming.py
wd360-0.1.0.dist-info/licenses/LICENSE
wd360-0.1.0.dist-info/METADATA
wd360-0.1.0.dist-info/WHEEL
wd360-0.1.0.dist-info/entry_points.txt
wd360-0.1.0.dist-info/top_level.txt
wd360-0.1.0.dist-info/RECORD
