Metadata-Version: 2.4
Name: wd360
Version: 0.1.0
Summary: Watchdog360 CLI framework for standardized Azure AI infra templates
Author-email: Watchdog360 <devnull@example.com>
License: MIT
Keywords: azure,arm-templates,infrastructure,ai,cli,devops
Classifier: Development Status :: 4 - Beta
Classifier: Intended Audience :: Developers
Classifier: Intended Audience :: System Administrators
Classifier: License :: OSI Approved :: MIT License
Classifier: Operating System :: OS Independent
Classifier: Programming Language :: Python :: 3
Classifier: Programming Language :: Python :: 3.10
Classifier: Programming Language :: Python :: 3.11
Classifier: Programming Language :: Python :: 3.12
Classifier: Programming Language :: Python :: 3.13
Classifier: Topic :: Software Development :: Libraries :: Python Modules
Classifier: Topic :: System :: Systems Administration
Classifier: Topic :: Utilities
Requires-Python: >=3.10
License-File: LICENSE
Requires-Dist: typer[all]>=0.12.0
Requires-Dist: pydantic>=2.7.0
Requires-Dist: pyyaml>=6.0.0
Dynamic: license-file
